cosyvoice_ttsfrd/__init__.py
cosyvoice_ttsfrd/post_install.py
cosyvoice_ttsfrd/bundled_files/ttsfrd-0.4.2-cp310-cp310-linux_x86_64.whl
cosyvoice_ttsfrd/bundled_files/ttsfrd_dependency-0.1-py3-none-any.whl
cosyvoice_ttsfrd-0.4.3.dist-info/licenses/LICENSE
cosyvoice_ttsfrd-0.4.3.dist-info/METADATA
cosyvoice_ttsfrd-0.4.3.dist-info/WHEEL
cosyvoice_ttsfrd-0.4.3.dist-info/entry_points.txt
cosyvoice_ttsfrd-0.4.3.dist-info/top_level.txt
cosyvoice_ttsfrd-0.4.3.dist-info/RECORD
