Metadata-Version: 2.4
Name: cosyvoice_ttsfrd
Version: 0.4.3
Summary: A wrapper package to install the ttsfrd package for CosyVoice.
Author-email: "jiaqi.sjq" <jiaqi.sjq@alibaba-inc.com>, xingchen song <sxc19@tsinghua.org.cn>
Project-URL: Homepage, https://github.com/xingchensong/CosyVoice-ttsfrd
Classifier: Programming Language :: Python :: 3
Classifier: Programming Language :: Python :: 3.10
Classifier: Operating System :: POSIX :: Linux
Classifier: Environment :: GPU :: NVIDIA CUDA
Classifier: Topic :: Scientific/Engineering :: Artificial Intelligence
Requires-Python: <3.11,>=3.10
License-File: LICENSE
Dynamic: license-file
